UQPyL/__init__.py
UQPyL/analysis/__init__.py
UQPyL/analysis/base.py
UQPyL/analysis/delta.py
UQPyL/analysis/fast.py
UQPyL/analysis/mars.py
UQPyL/analysis/morris.py
UQPyL/analysis/rbd_fast.py
UQPyL/analysis/rsa.py
UQPyL/analysis/sobol.py
UQPyL/doe/__init__.py
UQPyL/doe/base.py
UQPyL/doe/fast.py
UQPyL/doe/full_fact.py
UQPyL/doe/lhs.py
UQPyL/doe/morris.py
UQPyL/doe/random.py
UQPyL/doe/saltelli.py
UQPyL/doe/sobol.py
UQPyL/inference/__init__.py
UQPyL/inference/amh.py
UQPyL/inference/base.py
UQPyL/inference/chain.py
UQPyL/inference/demc.py
UQPyL/inference/dream_zs.py
UQPyL/inference/mh.py
UQPyL/inference/mh_gibbs.py
UQPyL/optimization/__init__.py
UQPyL/optimization/base.py
UQPyL/optimization/population.py
UQPyL/optimization/result.py
UQPyL/optimization/metric/__init__.py
UQPyL/optimization/metric/gd.py
UQPyL/optimization/metric/hv.py
UQPyL/optimization/metric/igd.py
UQPyL/optimization/moea/__init__.py
UQPyL/optimization/moea/moasmo.py
UQPyL/optimization/moea/moea_d.py
UQPyL/optimization/moea/nsga_ii.py
UQPyL/optimization/moea/nsga_iii.py
UQPyL/optimization/moea/rvea.py
UQPyL/optimization/soea/__init__.py
UQPyL/optimization/soea/abc.py
UQPyL/optimization/soea/asmo.py
UQPyL/optimization/soea/csa.py
UQPyL/optimization/soea/de.py
UQPyL/optimization/soea/ego.py
UQPyL/optimization/soea/ga.py
UQPyL/optimization/soea/ml_sce_ua.py
UQPyL/optimization/soea/pso.py
UQPyL/optimization/soea/sce_ua.py
UQPyL/optimization/util/__init__.py
UQPyL/optimization/util/crowding_distance.py
UQPyL/optimization/util/ga_operator.py
UQPyL/optimization/util/non_dominated_sort.py
UQPyL/optimization/util/tournament.py
UQPyL/optimization/util/uniform_point.py
UQPyL/problem/__init__.py
UQPyL/problem/base.py
UQPyL/problem/problem.py
UQPyL/problem/mop/DTLZ.py
UQPyL/problem/mop/ZDT.py
UQPyL/problem/mop/__init__.py
UQPyL/problem/sop/__init__.py
UQPyL/problem/sop/single_constraint_problem.py
UQPyL/problem/sop/single_simple_problem.py
uqpyl-2.1.5.dist-info/METADATA
uqpyl-2.1.5.dist-info/WHEEL
uqpyl-2.1.5.dist-info/top_level.txt
uqpyl-2.1.5.dist-info/RECORD
