Metadata-Version: 2.1
Name: UQPyL
Version: 2.1.5
Summary: A python package for parameter uncertainty quantification and optimization
Author: wmtSky
Author-email: wmtSky <wmtsky@hhu.edu.cn>
Classifier: Programming Language :: Python :: 3.8
Classifier: Programming Language :: Python :: 3.9
Classifier: Programming Language :: Python :: 3.10
Classifier: Programming Language :: Python :: 3.11
Classifier: Programming Language :: Python :: 3.12
Classifier: Programming Language :: Python :: 3.13
Classifier: License :: OSI Approved :: MIT License
Classifier: Operating System :: OS Independent
Requires-Dist: numpy<2
Requires-Dist: scipy
Requires-Dist: prettytable
Requires-Dist: xarray
Requires-Dist: netcdf4<1.7; python_version < "3.9"
Requires-Dist: netcdf4; python_version >= "3.9"
